{
  "kind": "youtube#video",
  "etag": "yOj0H_usQN5PrJYq65doPZPvozM",
  "id": "0ASconJZdAA",
  "snippet": {
    "publishedAt": "2018-12-17T07:00:01Z",
    "channelId": "UCk8GzjMOrta8yxDcKfylJYw",
    "title": "Diana Cleans The House to get toys",
    "description": "Diana and Roma want new toys. Mom offered to children clean the house first. Roma does not want to clean. Diana alone cleans the house and gets a lot of new toys.\nDiana`s INSTAGRAM https://www.instagram.com/kidsdianashow/\nSubscribe to Kids Diana Show - http://bit.ly/2k7NrSx Facebook https://www.facebook.com/KidsDianaShowOfficial/",
    "thumbnails": {
      "default": {
        "url": "https://i.ytimg.com/vi/0ASconJZdAA/default.jpg",
        "width": 120,
        "height": 90
      },
      "medium": {
        "url": "https://i.ytimg.com/vi/0ASconJZdAA/mqdefault.jpg",
        "width": 320,
        "height": 180
      },
      "high": {
        "url": "https://i.ytimg.com/vi/0ASconJZdAA/hqdefault.jpg",
        "width": 480,
        "height": 360
      },
      "standard": {
        "url": "https://i.ytimg.com/vi/0ASconJZdAA/sddefault.jpg",
        "width": 640,
        "height": 480
      },
      "maxres": {
        "url": "https://i.ytimg.com/vi/0ASconJZdAA/maxresdefault.jpg",
        "width": 1280,
        "height": 720
      }
    },
    "channelTitle": "✿ Kids Diana Show",
    "tags": [
      "toys",
      "kids toys",
      "pretend play",
      "kids",
      "cleans the house",
      "diana",
      "for kids",
      "рома и диана",
      "video for kids",
      "диана",
      "toy",
      "cleaning",
      "игрушки"
    ],
    "categoryId": "24",
    "liveBroadcastContent": "none",
    "defaultLanguage": "en",
    "localized": {
      "title": "Diana Cleans The House to get toys",
      "description": "Diana and Roma want new toys. Mom offered to children clean the house first. Roma does not want to clean. Diana alone cleans the house and gets a lot of new toys.\nDiana`s INSTAGRAM https://www.instagram.com/kidsdianashow/\nSubscribe to Kids Diana Show - http://bit.ly/2k7NrSx Facebook https://www.facebook.com/KidsDianaShowOfficial/"
    },
    "defaultAudioLanguage": "ru"
  },
  "contentDetails": {
    "duration": "PT11M39S",
    "dimension": "2d",
    "definition": "hd",
    "caption": "false",
    "licensedContent": false,
    "contentRating": {},
    "projection": "rectangular"
  },
  "status": {
    "uploadStatus": "processed",
    "privacyStatus": "public",
    "license": "youtube",
    "embeddable": true,
    "publicStatsViewable": false,
    "madeForKids": true
  },
  "statistics": {
    "viewCount": "138842327",
    "likeCount": "300765",
    "favoriteCount": "0"
  },
  "player": {
    "embedHtml": "<iframe width=\"480\" height=\"270\" src=\"//www.youtube.com/embed/0ASconJZdAA\" frameborder=\"0\" allow=\"accelerometer; autoplay; clipboard-write; encrypted-media; gyroscope; picture-in-picture; web-share\" referrerpolicy=\"strict-origin-when-cross-origin\" allowfullscreen></iframe>"
  },
  "topicDetails": {
    "topicCategories": [
      "https://en.wikipedia.org/wiki/Hobby",
      "https://en.wikipedia.org/wiki/Lifestyle_(sociology)"
    ]
  },
  "recordingDetails": {}
}