{
  "kind": "youtube#video",
  "etag": "YhATJSgFp07DMOSaJIzZDJNSGq8",
  "id": "5bnlcDYD_so",
  "snippet": {
    "publishedAt": "2018-11-11T07:00:00Z",
    "channelId": "UCk8GzjMOrta8yxDcKfylJYw",
    "title": "Diana Pretend Play Dress Up and New Make Up toys",
    "description": "Diana Pretend Play Dress Up and does makeup with her new Make Up toys. The girl wants to be fashionable and beautiful. But, going out into the street, she meets girls in exactly the same outfits as hers! Diana changes clothes over and over again to be the most fashionable and not like other girls. New video for kids\nDiana`s INSTAGRAM https://www.instagram.com/kidsdianashow/\nSubscribe to Kids Diana Show - http://bit.ly/2k7NrSx Facebook https://www.facebook.com/KidsDianaShowOfficial/",
    "thumbnails": {
      "default": {
        "url": "https://i.ytimg.com/vi/5bnlcDYD_so/default.jpg",
        "width": 120,
        "height": 90
      },
      "medium": {
        "url": "https://i.ytimg.com/vi/5bnlcDYD_so/mqdefault.jpg",
        "width": 320,
        "height": 180
      },
      "high": {
        "url": "https://i.ytimg.com/vi/5bnlcDYD_so/hqdefault.jpg",
        "width": 480,
        "height": 360
      },
      "standard": {
        "url": "https://i.ytimg.com/vi/5bnlcDYD_so/sddefault.jpg",
        "width": 640,
        "height": 480
      },
      "maxres": {
        "url": "https://i.ytimg.com/vi/5bnlcDYD_so/maxresdefault.jpg",
        "width": 1280,
        "height": 720
      }
    },
    "channelTitle": "✿ Kids Diana Show",
    "tags": [
      "pretend play",
      "dress up",
      "makeup",
      "make up",
      "kids make up",
      "makeup toys",
      "kids toys",
      "toy",
      "toys",
      "for kids",
      "diana",
      "диана",
      "new",
      "video for kids"
    ],
    "categoryId": "24",
    "liveBroadcastContent": "none",
    "defaultLanguage": "en",
    "localized": {
      "title": "Diana Pretend Play Dress Up and New Make Up toys",
      "description": "Diana Pretend Play Dress Up and does makeup with her new Make Up toys. The girl wants to be fashionable and beautiful. But, going out into the street, she meets girls in exactly the same outfits as hers! Diana changes clothes over and over again to be the most fashionable and not like other girls. New video for kids\nDiana`s INSTAGRAM https://www.instagram.com/kidsdianashow/\nSubscribe to Kids Diana Show - http://bit.ly/2k7NrSx Facebook https://www.facebook.com/KidsDianaShowOfficial/"
    },
    "defaultAudioLanguage": "ru"
  },
  "contentDetails": {
    "duration": "PT10M2S",
    "dimension": "2d",
    "definition": "hd",
    "caption": "false",
    "licensedContent": false,
    "contentRating": {},
    "projection": "rectangular"
  },
  "status": {
    "uploadStatus": "processed",
    "privacyStatus": "public",
    "license": "youtube",
    "embeddable": true,
    "publicStatsViewable": false,
    "madeForKids": true
  },
  "statistics": {
    "viewCount": "466121080",
    "likeCount": "1443459",
    "favoriteCount": "0"
  },
  "player": {
    "embedHtml": "<iframe width=\"480\" height=\"270\" src=\"//www.youtube.com/embed/5bnlcDYD_so\" frameborder=\"0\" allow=\"accelerometer; autoplay; clipboard-write; encrypted-media; gyroscope; picture-in-picture; web-share\" referrerpolicy=\"strict-origin-when-cross-origin\" allowfullscreen></iframe>"
  },
  "topicDetails": {
    "topicCategories": [
      "https://en.wikipedia.org/wiki/Hobby",
      "https://en.wikipedia.org/wiki/Lifestyle_(sociology)"
    ]
  },
  "recordingDetails": {}
}