{
  "kind": "youtube#video",
  "etag": "HLG03ozzANCDnp1z17r58mSVxy4",
  "id": "dFAnSq--srM",
  "snippet": {
    "publishedAt": "2024-04-13T12:30:31Z",
    "channelId": "UCk8GzjMOrta8yxDcKfylJYw",
    "title": "Diana cooks Pizza 🍕🍕 at Oliver's Cafe",
    "description": "Diana cooks Pizza at Oliver's Cafe. Join us for a delicious and fun cooking adventure with Diana in the kitchen.",
    "thumbnails": {
      "default": {
        "url": "https://i.ytimg.com/vi/dFAnSq--srM/default.jpg",
        "width": 120,
        "height": 90
      },
      "medium": {
        "url": "https://i.ytimg.com/vi/dFAnSq--srM/mqdefault.jpg",
        "width": 320,
        "height": 180
      },
      "high": {
        "url": "https://i.ytimg.com/vi/dFAnSq--srM/hqdefault.jpg",
        "width": 480,
        "height": 360
      },
      "standard": {
        "url": "https://i.ytimg.com/vi/dFAnSq--srM/sddefault.jpg",
        "width": 640,
        "height": 480
      },
      "maxres": {
        "url": "https://i.ytimg.com/vi/dFAnSq--srM/maxresdefault.jpg",
        "width": 1280,
        "height": 720
      }
    },
    "channelTitle": "✿ Kids Diana Show",
    "categoryId": "24",
    "liveBroadcastContent": "none",
    "defaultLanguage": "en-US",
    "localized": {
      "title": "Diana cooks Pizza 🍕🍕 at Oliver's Cafe",
      "description": "Diana cooks Pizza at Oliver's Cafe. Join us for a delicious and fun cooking adventure with Diana in the kitchen."
    },
    "defaultAudioLanguage": "en"
  },
  "contentDetails": {
    "duration": "PT50S",
    "dimension": "2d",
    "definition": "hd",
    "caption": "false",
    "licensedContent": true,
    "contentRating": {},
    "projection": "rectangular"
  },
  "status": {
    "uploadStatus": "processed",
    "privacyStatus": "public",
    "license": "youtube",
    "embeddable": true,
    "publicStatsViewable": false,
    "madeForKids": true
  },
  "statistics": {
    "viewCount": "366467",
    "likeCount": "11484",
    "favoriteCount": "0"
  },
  "player": {
    "embedHtml": "<iframe width=\"480\" height=\"270\" src=\"//www.youtube.com/embed/dFAnSq--srM\" frameborder=\"0\" allow=\"accelerometer; autoplay; clipboard-write; encrypted-media; gyroscope; picture-in-picture; web-share\" referrerpolicy=\"strict-origin-when-cross-origin\" allowfullscreen></iframe>"
  },
  "topicDetails": {
    "topicCategories": [
      "https://en.wikipedia.org/wiki/Food",
      "https://en.wikipedia.org/wiki/Lifestyle_(sociology)"
    ]
  },
  "recordingDetails": {}
}