{
  "kind": "youtube#video",
  "etag": "p9MX0Nvg4c4x4rMTveZF1yejy3I",
  "id": "NiGhXkqYyQg",
  "snippet": {
    "publishedAt": "2015-12-25T13:18:03Z",
    "channelId": "UCk8GzjMOrta8yxDcKfylJYw",
    "title": "✿ МЕДВЕДЬ-СКАЗОЧНИК Распаковка Перед Сном unboxing toys",
    "description": "МЕДВЕДЬ-СКАЗОЧНИК Распаковка Перед Сном \nunboxing toys\nhttps://youtu.be/NiGhXkqYyQg Facebook https://www.facebook.com/KidsDianaShowOfficial/",
    "thumbnails": {
      "default": {
        "url": "https://i.ytimg.com/vi/NiGhXkqYyQg/default.jpg",
        "width": 120,
        "height": 90
      },
      "medium": {
        "url": "https://i.ytimg.com/vi/NiGhXkqYyQg/mqdefault.jpg",
        "width": 320,
        "height": 180
      },
      "high": {
        "url": "https://i.ytimg.com/vi/NiGhXkqYyQg/hqdefault.jpg",
        "width": 480,
        "height": 360
      },
      "standard": {
        "url": "https://i.ytimg.com/vi/NiGhXkqYyQg/sddefault.jpg",
        "width": 640,
        "height": 480
      }
    },
    "channelTitle": "✿ Kids Diana Show",
    "tags": [
      "маленькая девочка раскрывает сюрпризы",
      "развивающие мультики",
      "детский канал",
      "сюрпризы для детей",
      "видео для детей",
      "детское видео",
      "детский влог",
      "киндер сюрприз",
      "игрушки",
      "Диана Шоу",
      "Diana Show",
      "обзор игрушек",
      "девочка играется игрушками",
      "VLOG",
      "малышь распаковывает игрушки",
      "маленькая девочка открывает сюрпризы",
      "распаковка",
      "Toys Review",
      "for children",
      "for kids",
      "online",
      "reality show online",
      "unboxing videos",
      "мис кети",
      "miss katy",
      "МЕДВЕДЬ-СКАЗОЧНИК"
    ],
    "categoryId": "22",
    "liveBroadcastContent": "none",
    "defaultLanguage": "ru",
    "localized": {
      "title": "✿ МЕДВЕДЬ-СКАЗОЧНИК Распаковка Перед Сном unboxing toys",
      "description": "МЕДВЕДЬ-СКАЗОЧНИК Распаковка Перед Сном \nunboxing toys\nhttps://youtu.be/NiGhXkqYyQg Facebook https://www.facebook.com/KidsDianaShowOfficial/"
    },
    "defaultAudioLanguage": "ru"
  },
  "contentDetails": {
    "duration": "PT3M48S",
    "dimension": "2d",
    "definition": "hd",
    "caption": "false",
    "licensedContent": false,
    "contentRating": {},
    "projection": "rectangular"
  },
  "status": {
    "uploadStatus": "processed",
    "privacyStatus": "public",
    "license": "youtube",
    "embeddable": true,
    "publicStatsViewable": false,
    "madeForKids": true
  },
  "statistics": {
    "viewCount": "517803",
    "favoriteCount": "0"
  },
  "player": {
    "embedHtml": "<iframe width=\"480\" height=\"270\" src=\"//www.youtube.com/embed/NiGhXkqYyQg\" frameborder=\"0\" allow=\"accelerometer; autoplay; clipboard-write; encrypted-media; gyroscope; picture-in-picture; web-share\" referrerpolicy=\"strict-origin-when-cross-origin\" allowfullscreen></iframe>"
  },
  "topicDetails": {
    "topicCategories": [
      "https://en.wikipedia.org/wiki/Hobby",
      "https://en.wikipedia.org/wiki/Lifestyle_(sociology)"
    ]
  },
  "recordingDetails": {}
}