{
  "kind": "youtube#video",
  "etag": "SrwCIilI_I9becp-yZxcS3nQskQ",
  "id": "OYzIUntnh70",
  "snippet": {
    "publishedAt": "2019-03-01T07:00:02Z",
    "channelId": "UCk8GzjMOrta8yxDcKfylJYw",
    "title": "Diana and Peppa Pig Theme Park",
    "description": "Diana and Roma having lots of fun at Peppa Pig World Theme Park. This is amusement park for children with the characters of their favorite cartoon. Diana and Roma visited Peppa Pig’s house, rode the rides, and jumped in the famous puddles that Peppa loves so much.\nDiana's INSTAGRAM https://www.instagram.com/kidsdianashow/\nSubscribe to Kids Diana Show - http://bit.ly/2k7NrSx #dianaandromacartoon Facebook https://www.facebook.com/KidsDianaShowOfficial/",
    "thumbnails": {
      "default": {
        "url": "https://i.ytimg.com/vi/OYzIUntnh70/default.jpg",
        "width": 120,
        "height": 90
      },
      "medium": {
        "url": "https://i.ytimg.com/vi/OYzIUntnh70/mqdefault.jpg",
        "width": 320,
        "height": 180
      },
      "high": {
        "url": "https://i.ytimg.com/vi/OYzIUntnh70/hqdefault.jpg",
        "width": 480,
        "height": 360
      },
      "standard": {
        "url": "https://i.ytimg.com/vi/OYzIUntnh70/sddefault.jpg",
        "width": 640,
        "height": 480
      },
      "maxres": {
        "url": "https://i.ytimg.com/vi/OYzIUntnh70/maxresdefault.jpg",
        "width": 1280,
        "height": 720
      }
    },
    "channelTitle": "✿ Kids Diana Show",
    "tags": [
      "peppa pig",
      "peppa pig world",
      "theme park",
      "amusement park",
      "for kids",
      "peppa",
      "diana and roma",
      "диана",
      "kids diana show",
      "diana",
      "diana and roma cartoon"
    ],
    "categoryId": "24",
    "liveBroadcastContent": "none",
    "defaultLanguage": "en",
    "localized": {
      "title": "Diana and Peppa Pig Theme Park",
      "description": "Diana and Roma having lots of fun at Peppa Pig World Theme Park. This is amusement park for children with the characters of their favorite cartoon. Diana and Roma visited Peppa Pig’s house, rode the rides, and jumped in the famous puddles that Peppa loves so much.\nDiana's INSTAGRAM https://www.instagram.com/kidsdianashow/\nSubscribe to Kids Diana Show - http://bit.ly/2k7NrSx #dianaandromacartoon Facebook https://www.facebook.com/KidsDianaShowOfficial/"
    },
    "defaultAudioLanguage": "en"
  },
  "contentDetails": {
    "duration": "PT12M1S",
    "dimension": "2d",
    "definition": "hd",
    "caption": "false",
    "licensedContent": false,
    "contentRating": {},
    "projection": "rectangular"
  },
  "status": {
    "uploadStatus": "processed",
    "privacyStatus": "public",
    "license": "youtube",
    "embeddable": true,
    "publicStatsViewable": false,
    "madeForKids": true
  },
  "statistics": {
    "viewCount": "172279877",
    "likeCount": "269436",
    "favoriteCount": "0"
  },
  "player": {
    "embedHtml": "<iframe width=\"480\" height=\"270\" src=\"//www.youtube.com/embed/OYzIUntnh70\" frameborder=\"0\" allow=\"accelerometer; autoplay; clipboard-write; encrypted-media; gyroscope; picture-in-picture; web-share\" referrerpolicy=\"strict-origin-when-cross-origin\" allowfullscreen></iframe>"
  },
  "topicDetails": {
    "topicCategories": [
      "https://en.wikipedia.org/wiki/Lifestyle_(sociology)",
      "https://en.wikipedia.org/wiki/Tourism"
    ]
  },
  "recordingDetails": {}
}