{
  "kind": "youtube#video",
  "etag": "D_LhPzlJWiNtZS_6P_xiMrHc5w0",
  "id": "QjGhCL6zw9M",
  "snippet": {
    "publishedAt": "2023-08-11T06:15:01Z",
    "channelId": "UCk8GzjMOrta8yxDcKfylJYw",
    "title": "Diana Roma and Oliver Explore the Mysterious Secret Room",
    "description": "Diana Roma and Oliver's thrilling adventure in the secret room\n00:00 Diana Roma and Oliver explore the mysterious Room\n04:46 Roma and Oliver magic transformer car story\nSubscribe to Kids Diana Show - http://bit.ly/2k7NrSx\nInstagram https://www.instagram.com/kidsdianashow/\n#DianaandRoma Facebook https://www.facebook.com/KidsDianaShowOfficial/",
    "thumbnails": {
      "default": {
        "url": "https://i.ytimg.com/vi/QjGhCL6zw9M/default.jpg",
        "width": 120,
        "height": 90
      },
      "medium": {
        "url": "https://i.ytimg.com/vi/QjGhCL6zw9M/mqdefault.jpg",
        "width": 320,
        "height": 180
      },
      "high": {
        "url": "https://i.ytimg.com/vi/QjGhCL6zw9M/hqdefault.jpg",
        "width": 480,
        "height": 360
      },
      "standard": {
        "url": "https://i.ytimg.com/vi/QjGhCL6zw9M/sddefault.jpg",
        "width": 640,
        "height": 480
      },
      "maxres": {
        "url": "https://i.ytimg.com/vi/QjGhCL6zw9M/maxresdefault.jpg",
        "width": 1280,
        "height": 720
      }
    },
    "channelTitle": "✿ Kids Diana Show",
    "tags": [
      "diana and roma",
      "cartoon",
      "roma and diana",
      "diana y roma",
      "diana roma",
      "diana",
      "roma",
      "oliver",
      "diana and roma english",
      "kids diana show",
      "diana and oliver",
      "secret room",
      "mysterious room"
    ],
    "categoryId": "24",
    "liveBroadcastContent": "none",
    "defaultLanguage": "en-US",
    "localized": {
      "title": "Diana Roma and Oliver Explore the Mysterious Secret Room",
      "description": "Diana Roma and Oliver's thrilling adventure in the secret room\n00:00 Diana Roma and Oliver explore the mysterious Room\n04:46 Roma and Oliver magic transformer car story\nSubscribe to Kids Diana Show - http://bit.ly/2k7NrSx\nInstagram https://www.instagram.com/kidsdianashow/\n#DianaandRoma Facebook https://www.facebook.com/KidsDianaShowOfficial/"
    },
    "defaultAudioLanguage": "en"
  },
  "contentDetails": {
    "duration": "PT10M1S",
    "dimension": "2d",
    "definition": "hd",
    "caption": "false",
    "licensedContent": true,
    "contentRating": {},
    "projection": "rectangular"
  },
  "status": {
    "uploadStatus": "processed",
    "privacyStatus": "public",
    "license": "youtube",
    "embeddable": true,
    "publicStatsViewable": false,
    "madeForKids": true
  },
  "statistics": {
    "viewCount": "102598392",
    "likeCount": "137378",
    "favoriteCount": "0"
  },
  "player": {
    "embedHtml": "<iframe width=\"480\" height=\"270\" src=\"//www.youtube.com/embed/QjGhCL6zw9M\" frameborder=\"0\" allow=\"accelerometer; autoplay; clipboard-write; encrypted-media; gyroscope; picture-in-picture; web-share\" referrerpolicy=\"strict-origin-when-cross-origin\" allowfullscreen></iframe>"
  },
  "topicDetails": {
    "topicCategories": [
      "https://en.wikipedia.org/wiki/Hobby",
      "https://en.wikipedia.org/wiki/Lifestyle_(sociology)"
    ]
  },
  "recordingDetails": {}
}