{
  "kind": "youtube#video",
  "etag": "TDVwH__ho4gSUpgzfYmprF4JjXc",
  "id": "RV9CrP1Tkvk",
  "snippet": {
    "publishedAt": "2022-06-02T06:02:29Z",
    "channelId": "UCk8GzjMOrta8yxDcKfylJYw",
    "title": "Diana and Roma came up with How to Entertain baby Oliver | Fun Toddler Activities",
    "description": "Baby Oliver wants to play. Diana and Roma will show how you can entertain the baby and play together with him. Fun Toddler Activities to do at home.\nThanks for watching!\nSubscribe to Kids Diana Show - http://bit.ly/2k7NrSx\nInstagram https://www.instagram.com/kidsdianashow/\n#DianaandRoma Facebook https://www.facebook.com/KidsDianaShowOfficial/",
    "thumbnails": {
      "default": {
        "url": "https://i.ytimg.com/vi/RV9CrP1Tkvk/default.jpg",
        "width": 120,
        "height": 90
      },
      "medium": {
        "url": "https://i.ytimg.com/vi/RV9CrP1Tkvk/mqdefault.jpg",
        "width": 320,
        "height": 180
      },
      "high": {
        "url": "https://i.ytimg.com/vi/RV9CrP1Tkvk/hqdefault.jpg",
        "width": 480,
        "height": 360
      },
      "standard": {
        "url": "https://i.ytimg.com/vi/RV9CrP1Tkvk/sddefault.jpg",
        "width": 640,
        "height": 480
      },
      "maxres": {
        "url": "https://i.ytimg.com/vi/RV9CrP1Tkvk/maxresdefault.jpg",
        "width": 1280,
        "height": 720
      }
    },
    "channelTitle": "✿ Kids Diana Show",
    "tags": [
      "diana and roma",
      "diana",
      "cartoon",
      "roma and diana",
      "diana y roma",
      "diana roma",
      "entertain baby",
      "how to entertain a baby",
      "toddler activities",
      "toddler activities 1 year old",
      "toddler activities at home",
      "easy toddler activities",
      "toddler",
      "activities for baby",
      "kids videos",
      "diana and oliver",
      "baby oliver",
      "kids video",
      "oliver",
      "baby"
    ],
    "categoryId": "19",
    "liveBroadcastContent": "none",
    "defaultLanguage": "en-US",
    "localized": {
      "title": "Diana and Roma came up with How to Entertain baby Oliver | Fun Toddler Activities",
      "description": "Baby Oliver wants to play. Diana and Roma will show how you can entertain the baby and play together with him. Fun Toddler Activities to do at home.\nThanks for watching!\nSubscribe to Kids Diana Show - http://bit.ly/2k7NrSx\nInstagram https://www.instagram.com/kidsdianashow/\n#DianaandRoma Facebook https://www.facebook.com/KidsDianaShowOfficial/"
    },
    "defaultAudioLanguage": "en"
  },
  "contentDetails": {
    "duration": "PT3M33S",
    "dimension": "2d",
    "definition": "hd",
    "caption": "false",
    "licensedContent": true,
    "contentRating": {},
    "projection": "rectangular"
  },
  "status": {
    "uploadStatus": "processed",
    "privacyStatus": "public",
    "license": "youtube",
    "embeddable": true,
    "publicStatsViewable": false,
    "madeForKids": true
  },
  "statistics": {
    "viewCount": "53376789",
    "likeCount": "128333",
    "favoriteCount": "0"
  },
  "player": {
    "embedHtml": "<iframe width=\"480\" height=\"270\" src=\"//www.youtube.com/embed/RV9CrP1Tkvk\" frameborder=\"0\" allow=\"accelerometer; autoplay; clipboard-write; encrypted-media; gyroscope; picture-in-picture; web-share\" referrerpolicy=\"strict-origin-when-cross-origin\" allowfullscreen></iframe>"
  },
  "topicDetails": {
    "topicCategories": [
      "https://en.wikipedia.org/wiki/Lifestyle_(sociology)"
    ]
  },
  "recordingDetails": {}
}